[{"faceId":"579a25af-5bef-44af-9ee7-4743a89d728e","faceRectangle":{"top":39,"left":27,"width":73,"height":73},"faceAttributes":{"smile":0.787,"headPose":{"pitch":-2.3,"roll":-0.4,"yaw":-5.9},"gender":"female","age":24.0,"facialHair":{"moustache":0.0,"beard":0.0,"sideburns":0.0},"glasses":"SwimmingGoggles","emotion":{"anger":0.006,"contempt":0.0,"disgust":0.206,"fear":0.0,"happiness":0.787,"neutral":0.0,"sadness":0.0,"surprise":0.0},"blur":{"blurLevel":"medium","value":0.55},"exposure":{"exposureLevel":"goodExposure","value":0.64},"noise":{"noiseLevel":"medium","value":0.55},"makeup":{"eyeMakeup":true,"lipMakeup":false},"accessories":[{"type":"glasses","confidence":0.95},{"type":"headwear","confidence":1.0}],"occlusion":{"foreheadOccluded":true,"eyeOccluded":false,"mouthOccluded":false},"hair":{"bald":0.0,"invisible":true,"hairColor":[]}}}]