[{"faceId":"55816737-2a82-4e55-84ce-de427bf3c889","faceRectangle":{"top":39,"left":29,"width":71,"height":71},"faceAttributes":{"smile":0.98,"headPose":{"pitch":9.6,"roll":-1.1,"yaw":-1.2},"gender":"female","age":50.0,"facialHair":{"moustache":0.0,"beard":0.0,"sideburns":0.0},"glasses":"ReadingGlasses","emotion":{"anger":0.0,"contempt":0.0,"disgust":0.0,"fear":0.0,"happiness":0.98,"neutral":0.0,"sadness":0.019,"surprise":0.0},"blur":{"blurLevel":"low","value":0.04},"exposure":{"exposureLevel":"goodExposure","value":0.59},"noise":{"noiseLevel":"low","value":0.0},"makeup":{"eyeMakeup":false,"lipMakeup":true},"accessories":[{"type":"glasses","confidence":0.99}],"occlusion":{"foreheadOccluded":false,"eyeOccluded":false,"mouthOccluded":false},"hair":{"bald":0.04,"invisible":false,"hairColor":[{"color":"black","confidence":0.99},{"color":"brown","confidence":0.9},{"color":"gray","confidence":0.47},{"color":"other","confidence":0.38},{"color":"red","confidence":0.05},{"color":"blond","confidence":0.02}]}}}]