[{"faceId":"b4f886ad-87e4-455a-bbfb-3a07cce013ef","faceRectangle":{"top":43,"left":31,"width":67,"height":67},"faceAttributes":{"smile":0.018,"headPose":{"pitch":-5.5,"roll":-1.4,"yaw":32.8},"gender":"female","age":21.0,"facialHair":{"moustache":0.0,"beard":0.0,"sideburns":0.0},"glasses":"NoGlasses","emotion":{"anger":0.0,"contempt":0.001,"disgust":0.0,"fear":0.0,"happiness":0.018,"neutral":0.955,"sadness":0.024,"surprise":0.002},"blur":{"blurLevel":"low","value":0.02},"exposure":{"exposureLevel":"goodExposure","value":0.6},"noise":{"noiseLevel":"medium","value":0.45},"makeup":{"eyeMakeup":true,"lipMakeup":true},"accessories":[],"occlusion":{"foreheadOccluded":false,"eyeOccluded":false,"mouthOccluded":false},"hair":{"bald":0.07,"invisible":false,"hairColor":[{"color":"brown","confidence":0.95},{"color":"blond","confidence":0.89},{"color":"red","confidence":0.33},{"color":"gray","confidence":0.25},{"color":"black","confidence":0.2},{"color":"other","confidence":0.15}]}}}]