[{"faceId":"c9c83c46-c173-402b-80a3-8b14afb56009","faceRectangle":{"top":40,"left":24,"width":75,"height":75},"faceAttributes":{"smile":0.999,"headPose":{"pitch":-9.7,"roll":1.2,"yaw":-34.3},"gender":"female","age":43.0,"facialHair":{"moustache":0.0,"beard":0.0,"sideburns":0.0},"glasses":"NoGlasses","emotion":{"anger":0.0,"contempt":0.0,"disgust":0.0,"fear":0.0,"happiness":0.999,"neutral":0.0,"sadness":0.001,"surprise":0.0},"blur":{"blurLevel":"low","value":0.0},"exposure":{"exposureLevel":"goodExposure","value":0.59},"noise":{"noiseLevel":"low","value":0.0},"makeup":{"eyeMakeup":true,"lipMakeup":false},"accessories":[],"occlusion":{"foreheadOccluded":false,"eyeOccluded":false,"mouthOccluded":false},"hair":{"bald":0.81,"invisible":false,"hairColor":[]}}}]