[{"faceId":"6e5ffb02-e67d-44c0-9a03-36e2a37cf0c2","faceRectangle":{"top":40,"left":27,"width":71,"height":71},"faceAttributes":{"smile":0.969,"headPose":{"pitch":-6.3,"roll":0.2,"yaw":-22.0},"gender":"male","age":0.0,"facialHair":{"moustache":0.0,"beard":0.0,"sideburns":0.0},"glasses":"NoGlasses","emotion":{"anger":0.0,"contempt":0.0,"disgust":0.0,"fear":0.0,"happiness":0.969,"neutral":0.001,"sadness":0.03,"surprise":0.0},"blur":{"blurLevel":"medium","value":0.5},"exposure":{"exposureLevel":"goodExposure","value":0.7},"noise":{"noiseLevel":"low","value":0.0},"makeup":{"eyeMakeup":false,"lipMakeup":false},"accessories":[],"occlusion":{"foreheadOccluded":false,"eyeOccluded":false,"mouthOccluded":false},"hair":{"bald":0.16,"invisible":false,"hairColor":[{"color":"blond","confidence":0.96},{"color":"brown","confidence":0.46},{"color":"other","confidence":0.41},{"color":"gray","confidence":0.39},{"color":"red","confidence":0.28},{"color":"black","confidence":0.2}]}}}]