[{"faceId":"bb8dfd1c-0710-41e6-991f-c611ade4eb22","faceRectangle":{"top":40,"left":26,"width":72,"height":72},"faceAttributes":{"smile":0.0,"headPose":{"pitch":-2.5,"roll":-1.1,"yaw":-22.6},"gender":"male","age":5.0,"facialHair":{"moustache":0.0,"beard":0.0,"sideburns":0.0},"glasses":"NoGlasses","emotion":{"anger":0.025,"contempt":0.008,"disgust":0.001,"fear":0.001,"happiness":0.0,"neutral":0.89,"sadness":0.072,"surprise":0.003},"blur":{"blurLevel":"low","value":0.16},"exposure":{"exposureLevel":"goodExposure","value":0.34},"noise":{"noiseLevel":"low","value":0.15},"makeup":{"eyeMakeup":false,"lipMakeup":false},"accessories":[],"occlusion":{"foreheadOccluded":false,"eyeOccluded":false,"mouthOccluded":false},"hair":{"bald":0.61,"invisible":false,"hairColor":[{"color":"black","confidence":0.95},{"color":"brown","confidence":0.94},{"color":"blond","confidence":0.45},{"color":"gray","confidence":0.35},{"color":"other","confidence":0.14},{"color":"red","confidence":0.05}]}}}]