[{"faceId":"54da1af5-ce91-4a21-8020-fc92422987cd","faceRectangle":{"top":40,"left":29,"width":69,"height":69},"faceAttributes":{"smile":1.0,"headPose":{"pitch":-3.5,"roll":1.8,"yaw":-13.1},"gender":"female","age":36.0,"facialHair":{"moustache":0.0,"beard":0.0,"sideburns":0.0},"glasses":"NoGlasses","emotion":{"anger":0.0,"contempt":0.0,"disgust":0.0,"fear":0.0,"happiness":1.0,"neutral":0.0,"sadness":0.0,"surprise":0.0},"blur":{"blurLevel":"low","value":0.0},"exposure":{"exposureLevel":"goodExposure","value":0.61},"noise":{"noiseLevel":"low","value":0.0},"makeup":{"eyeMakeup":true,"lipMakeup":true},"accessories":[],"occlusion":{"foreheadOccluded":false,"eyeOccluded":false,"mouthOccluded":false},"hair":{"bald":0.04,"invisible":false,"hairColor":[{"color":"black","confidence":1.0},{"color":"brown","confidence":0.7},{"color":"gray","confidence":0.57},{"color":"other","confidence":0.53},{"color":"red","confidence":0.02},{"color":"blond","confidence":0.02}]}}}]