[{"faceId":"faf5739b-8e31-490d-aa06-8b82e867b2ae","faceRectangle":{"top":40,"left":29,"width":70,"height":70},"faceAttributes":{"smile":0.992,"headPose":{"pitch":-4.9,"roll":2.3,"yaw":4.7},"gender":"male","age":63.0,"facialHair":{"moustache":0.1,"beard":0.1,"sideburns":0.1},"glasses":"ReadingGlasses","emotion":{"anger":0.0,"contempt":0.0,"disgust":0.0,"fear":0.0,"happiness":0.992,"neutral":0.008,"sadness":0.0,"surprise":0.0},"blur":{"blurLevel":"medium","value":0.7},"exposure":{"exposureLevel":"goodExposure","value":0.69},"noise":{"noiseLevel":"medium","value":0.34},"makeup":{"eyeMakeup":true,"lipMakeup":true},"accessories":[{"type":"glasses","confidence":0.86}],"occlusion":{"foreheadOccluded":false,"eyeOccluded":false,"mouthOccluded":false},"hair":{"bald":0.39,"invisible":false,"hairColor":[{"color":"gray","confidence":1.0},{"color":"black","confidence":0.63},{"color":"blond","confidence":0.54},{"color":"other","confidence":0.49},{"color":"brown","confidence":0.12},{"color":"red","confidence":0.0}]}}}]