[{"faceId":"1d32618f-aca3-432e-8838-78cee5a8393d","faceRectangle":{"top":40,"left":29,"width":71,"height":71},"faceAttributes":{"smile":0.0,"headPose":{"pitch":-1.7,"roll":-1.2,"yaw":4.3},"gender":"male","age":4.0,"facialHair":{"moustache":0.0,"beard":0.0,"sideburns":0.0},"glasses":"NoGlasses","emotion":{"anger":0.0,"contempt":0.0,"disgust":0.0,"fear":0.0,"happiness":0.0,"neutral":0.846,"sadness":0.154,"surprise":0.0},"blur":{"blurLevel":"low","value":0.07},"exposure":{"exposureLevel":"overExposure","value":0.83},"noise":{"noiseLevel":"low","value":0.0},"makeup":{"eyeMakeup":false,"lipMakeup":false},"accessories":[],"occlusion":{"foreheadOccluded":false,"eyeOccluded":false,"mouthOccluded":false},"hair":{"bald":0.02,"invisible":false,"hairColor":[{"color":"blond","confidence":1.0},{"color":"gray","confidence":0.57},{"color":"brown","confidence":0.39},{"color":"red","confidence":0.32},{"color":"other","confidence":0.2},{"color":"black","confidence":0.01}]}}}]