[{"faceId":"6b932c80-cad6-43fe-9408-8d8d258f36a3","faceRectangle":{"top":38,"left":27,"width":72,"height":72},"faceAttributes":{"smile":1.0,"headPose":{"pitch":5.0,"roll":2.6,"yaw":-5.1},"gender":"male","age":37.0,"facialHair":{"moustache":0.1,"beard":0.1,"sideburns":0.1},"glasses":"NoGlasses","emotion":{"anger":0.0,"contempt":0.0,"disgust":0.0,"fear":0.0,"happiness":1.0,"neutral":0.0,"sadness":0.0,"surprise":0.0},"blur":{"blurLevel":"low","value":0.16},"exposure":{"exposureLevel":"goodExposure","value":0.44},"noise":{"noiseLevel":"medium","value":0.59},"makeup":{"eyeMakeup":false,"lipMakeup":false},"accessories":[],"occlusion":{"foreheadOccluded":false,"eyeOccluded":false,"mouthOccluded":false},"hair":{"bald":0.03,"invisible":false,"hairColor":[{"color":"brown","confidence":1.0},{"color":"blond","confidence":0.87},{"color":"red","confidence":0.4},{"color":"gray","confidence":0.2},{"color":"black","confidence":0.07},{"color":"other","confidence":0.02}]}}}]