[{"faceId":"b9cf0d02-3cde-4cbb-913c-a3e9e65ef394","faceRectangle":{"top":38,"left":25,"width":76,"height":76},"faceAttributes":{"smile":0.203,"headPose":{"pitch":3.5,"roll":5.2,"yaw":-11.7},"gender":"female","age":39.0,"facialHair":{"moustache":0.0,"beard":0.0,"sideburns":0.0},"glasses":"ReadingGlasses","emotion":{"anger":0.0,"contempt":0.002,"disgust":0.0,"fear":0.0,"happiness":0.203,"neutral":0.792,"sadness":0.002,"surprise":0.0},"blur":{"blurLevel":"medium","value":0.42},"exposure":{"exposureLevel":"goodExposure","value":0.46},"noise":{"noiseLevel":"low","value":0.0},"makeup":{"eyeMakeup":false,"lipMakeup":false},"accessories":[{"type":"glasses","confidence":0.98},{"type":"headwear","confidence":1.0}],"occlusion":{"foreheadOccluded":true,"eyeOccluded":false,"mouthOccluded":false},"hair":{"bald":0.0,"invisible":true,"hairColor":[]}}}]