[{"faceId":"9f64dc38-bbeb-4a8b-9617-33f6937d5430","faceRectangle":{"top":38,"left":26,"width":75,"height":75},"faceAttributes":{"smile":0.0,"headPose":{"pitch":9.7,"roll":2.9,"yaw":3.1},"gender":"male","age":53.0,"facialHair":{"moustache":0.1,"beard":0.4,"sideburns":0.1},"glasses":"NoGlasses","emotion":{"anger":0.03,"contempt":0.023,"disgust":0.002,"fear":0.002,"happiness":0.0,"neutral":0.902,"sadness":0.035,"surprise":0.005},"blur":{"blurLevel":"high","value":0.8},"exposure":{"exposureLevel":"goodExposure","value":0.68},"noise":{"noiseLevel":"medium","value":0.63},"makeup":{"eyeMakeup":false,"lipMakeup":false},"accessories":[],"occlusion":{"foreheadOccluded":false,"eyeOccluded":false,"mouthOccluded":false},"hair":{"bald":0.1,"invisible":false,"hairColor":[{"color":"gray","confidence":0.98},{"color":"blond","confidence":0.85},{"color":"brown","confidence":0.6},{"color":"black","confidence":0.28},{"color":"other","confidence":0.2},{"color":"red","confidence":0.02}]}}}]