[{"faceId":"325c9379-83e9-4ee4-8a87-21820c598204","faceRectangle":{"top":39,"left":28,"width":70,"height":70},"faceAttributes":{"smile":1.0,"headPose":{"pitch":-0.7,"roll":1.9,"yaw":-8.0},"gender":"male","age":19.0,"facialHair":{"moustache":0.1,"beard":0.1,"sideburns":0.1},"glasses":"NoGlasses","emotion":{"anger":0.0,"contempt":0.0,"disgust":0.0,"fear":0.0,"happiness":1.0,"neutral":0.0,"sadness":0.0,"surprise":0.0},"blur":{"blurLevel":"low","value":0.06},"exposure":{"exposureLevel":"goodExposure","value":0.68},"noise":{"noiseLevel":"low","value":0.01},"makeup":{"eyeMakeup":false,"lipMakeup":false},"accessories":[{"type":"headwear","confidence":0.99}],"occlusion":{"foreheadOccluded":true,"eyeOccluded":false,"mouthOccluded":false},"hair":{"bald":0.0,"invisible":true,"hairColor":[]}}}]