[{"faceId":"333742f1-92f6-48df-a29a-d1b94aaeca5a","faceRectangle":{"top":41,"left":29,"width":70,"height":70},"faceAttributes":{"smile":0.199,"headPose":{"pitch":2.9,"roll":1.9,"yaw":13.9},"gender":"male","age":63.0,"facialHair":{"moustache":0.1,"beard":0.1,"sideburns":0.1},"glasses":"ReadingGlasses","emotion":{"anger":0.0,"contempt":0.001,"disgust":0.0,"fear":0.0,"happiness":0.199,"neutral":0.799,"sadness":0.0,"surprise":0.001},"blur":{"blurLevel":"medium","value":0.73},"exposure":{"exposureLevel":"goodExposure","value":0.61},"noise":{"noiseLevel":"high","value":0.73},"makeup":{"eyeMakeup":false,"lipMakeup":false},"accessories":[{"type":"glasses","confidence":0.99}],"occlusion":{"foreheadOccluded":false,"eyeOccluded":false,"mouthOccluded":false},"hair":{"bald":0.12,"invisible":false,"hairColor":[{"color":"gray","confidence":0.99},{"color":"other","confidence":0.62},{"color":"black","confidence":0.59},{"color":"blond","confidence":0.56},{"color":"brown","confidence":0.1},{"color":"red","confidence":0.02}]}}}]