[{"faceId":"0a2ee9a1-bd7f-48cf-a30c-3dbe3b54c837","faceRectangle":{"top":39,"left":28,"width":73,"height":73},"faceAttributes":{"smile":1.0,"headPose":{"pitch":5.9,"roll":0.5,"yaw":10.3},"gender":"male","age":57.0,"facialHair":{"moustache":0.1,"beard":0.1,"sideburns":0.1},"glasses":"NoGlasses","emotion":{"anger":0.0,"contempt":0.0,"disgust":0.0,"fear":0.0,"happiness":1.0,"neutral":0.0,"sadness":0.0,"surprise":0.0},"blur":{"blurLevel":"medium","value":0.45},"exposure":{"exposureLevel":"goodExposure","value":0.63},"noise":{"noiseLevel":"low","value":0.1},"makeup":{"eyeMakeup":false,"lipMakeup":false},"accessories":[],"occlusion":{"foreheadOccluded":false,"eyeOccluded":false,"mouthOccluded":false},"hair":{"bald":0.01,"invisible":false,"hairColor":[{"color":"gray","confidence":0.94},{"color":"brown","confidence":0.9},{"color":"black","confidence":0.86},{"color":"other","confidence":0.24},{"color":"blond","confidence":0.09},{"color":"red","confidence":0.04}]}}}]