[{"faceId":"47d45fa6-923b-4ced-bb4b-f8be8605ae31","faceRectangle":{"top":40,"left":27,"width":74,"height":74},"faceAttributes":{"smile":1.0,"headPose":{"pitch":-5.3,"roll":1.2,"yaw":2.9},"gender":"male","age":64.0,"facialHair":{"moustache":0.6,"beard":0.4,"sideburns":0.4},"glasses":"NoGlasses","emotion":{"anger":0.0,"contempt":0.0,"disgust":0.0,"fear":0.0,"happiness":1.0,"neutral":0.0,"sadness":0.0,"surprise":0.0},"blur":{"blurLevel":"low","value":0.24},"exposure":{"exposureLevel":"goodExposure","value":0.7},"noise":{"noiseLevel":"high","value":0.78},"makeup":{"eyeMakeup":false,"lipMakeup":false},"accessories":[],"occlusion":{"foreheadOccluded":false,"eyeOccluded":false,"mouthOccluded":false},"hair":{"bald":0.9,"invisible":false,"hairColor":[]}}}]