[{"faceId":"03a25251-ebe9-40fb-bc2a-f0b0d9ab3f13","faceRectangle":{"top":41,"left":28,"width":72,"height":72},"faceAttributes":{"smile":0.645,"headPose":{"pitch":-17.1,"roll":-1.0,"yaw":-14.7},"gender":"male","age":33.0,"facialHair":{"moustache":0.1,"beard":0.1,"sideburns":0.1},"glasses":"NoGlasses","emotion":{"anger":0.0,"contempt":0.113,"disgust":0.0,"fear":0.0,"happiness":0.645,"neutral":0.241,"sadness":0.0,"surprise":0.0},"blur":{"blurLevel":"low","value":0.07},"exposure":{"exposureLevel":"goodExposure","value":0.58},"noise":{"noiseLevel":"low","value":0.0},"makeup":{"eyeMakeup":false,"lipMakeup":false},"accessories":[],"occlusion":{"foreheadOccluded":false,"eyeOccluded":false,"mouthOccluded":false},"hair":{"bald":0.02,"invisible":false,"hairColor":[{"color":"brown","confidence":1.0},{"color":"black","confidence":0.56},{"color":"red","confidence":0.29},{"color":"blond","confidence":0.18},{"color":"gray","confidence":0.15},{"color":"other","confidence":0.03}]}}}]