[{"faceId":"48832bf7-bfd0-4ede-8b03-2d171f650ee3","faceRectangle":{"top":39,"left":30,"width":68,"height":68},"faceAttributes":{"smile":1.0,"headPose":{"pitch":0.8,"roll":3.2,"yaw":-1.5},"gender":"male","age":8.0,"facialHair":{"moustache":0.0,"beard":0.0,"sideburns":0.0},"glasses":"NoGlasses","emotion":{"anger":0.0,"contempt":0.0,"disgust":0.0,"fear":0.0,"happiness":1.0,"neutral":0.0,"sadness":0.0,"surprise":0.0},"blur":{"blurLevel":"low","value":0.0},"exposure":{"exposureLevel":"goodExposure","value":0.72},"noise":{"noiseLevel":"low","value":0.0},"makeup":{"eyeMakeup":false,"lipMakeup":false},"accessories":[],"occlusion":{"foreheadOccluded":false,"eyeOccluded":false,"mouthOccluded":false},"hair":{"bald":0.13,"invisible":false,"hairColor":[{"color":"black","confidence":0.96},{"color":"brown","confidence":0.94},{"color":"blond","confidence":0.28},{"color":"gray","confidence":0.24},{"color":"other","confidence":0.19},{"color":"red","confidence":0.08}]}}}]