[{"faceId":"487937a7-6cfa-49d6-89a1-70975979c8a7","faceRectangle":{"top":41,"left":28,"width":68,"height":68},"faceAttributes":{"smile":0.904,"headPose":{"pitch":-3.7,"roll":-1.3,"yaw":-24.2},"gender":"male","age":1.0,"facialHair":{"moustache":0.0,"beard":0.0,"sideburns":0.0},"glasses":"NoGlasses","emotion":{"anger":0.0,"contempt":0.0,"disgust":0.0,"fear":0.0,"happiness":0.904,"neutral":0.079,"sadness":0.0,"surprise":0.015},"blur":{"blurLevel":"medium","value":0.57},"exposure":{"exposureLevel":"overExposure","value":0.82},"noise":{"noiseLevel":"medium","value":0.7},"makeup":{"eyeMakeup":false,"lipMakeup":false},"accessories":[],"occlusion":{"foreheadOccluded":false,"eyeOccluded":false,"mouthOccluded":false},"hair":{"bald":0.06,"invisible":false,"hairColor":[{"color":"blond","confidence":0.96},{"color":"brown","confidence":0.81},{"color":"red","confidence":0.36},{"color":"gray","confidence":0.26},{"color":"other","confidence":0.23},{"color":"black","confidence":0.13}]}}}]