[{"faceId":"30aab4d4-8f3f-4826-9d68-8f809e6664dc","faceRectangle":{"top":39,"left":29,"width":71,"height":71},"faceAttributes":{"smile":1.0,"headPose":{"pitch":13.8,"roll":1.2,"yaw":7.6},"gender":"female","age":48.0,"facialHair":{"moustache":0.0,"beard":0.0,"sideburns":0.0},"glasses":"NoGlasses","emotion":{"anger":0.0,"contempt":0.0,"disgust":0.0,"fear":0.0,"happiness":1.0,"neutral":0.0,"sadness":0.0,"surprise":0.0},"blur":{"blurLevel":"medium","value":0.36},"exposure":{"exposureLevel":"goodExposure","value":0.69},"noise":{"noiseLevel":"medium","value":0.66},"makeup":{"eyeMakeup":true,"lipMakeup":true},"accessories":[],"occlusion":{"foreheadOccluded":false,"eyeOccluded":false,"mouthOccluded":false},"hair":{"bald":0.04,"invisible":false,"hairColor":[{"color":"brown","confidence":1.0},{"color":"blond","confidence":0.82},{"color":"red","confidence":0.65},{"color":"gray","confidence":0.17},{"color":"black","confidence":0.03},{"color":"other","confidence":0.03}]}}}]