[{"faceId":"57964b31-ecbd-4a7f-a8ad-c4464c030786","faceRectangle":{"top":40,"left":25,"width":75,"height":75},"faceAttributes":{"smile":0.997,"headPose":{"pitch":-1.4,"roll":-0.3,"yaw":-8.4},"gender":"female","age":20.0,"facialHair":{"moustache":0.0,"beard":0.0,"sideburns":0.0},"glasses":"NoGlasses","emotion":{"anger":0.0,"contempt":0.0,"disgust":0.0,"fear":0.0,"happiness":0.997,"neutral":0.002,"sadness":0.0,"surprise":0.001},"blur":{"blurLevel":"low","value":0.21},"exposure":{"exposureLevel":"goodExposure","value":0.45},"noise":{"noiseLevel":"low","value":0.0},"makeup":{"eyeMakeup":true,"lipMakeup":true},"accessories":[],"occlusion":{"foreheadOccluded":false,"eyeOccluded":false,"mouthOccluded":false},"hair":{"bald":0.06,"invisible":false,"hairColor":[{"color":"black","confidence":1.0},{"color":"brown","confidence":0.91},{"color":"other","confidence":0.38},{"color":"gray","confidence":0.27},{"color":"red","confidence":0.03},{"color":"blond","confidence":0.02}]}}}]