[{"faceId":"2c33623d-9885-4ef6-bf2c-83ca26f80c62","faceRectangle":{"top":40,"left":27,"width":74,"height":74},"faceAttributes":{"smile":0.018,"headPose":{"pitch":-5.1,"roll":0.8,"yaw":-8.9},"gender":"male","age":34.0,"facialHair":{"moustache":0.1,"beard":0.1,"sideburns":0.1},"glasses":"NoGlasses","emotion":{"anger":0.0,"contempt":0.0,"disgust":0.0,"fear":0.0,"happiness":0.018,"neutral":0.982,"sadness":0.0,"surprise":0.0},"blur":{"blurLevel":"low","value":0.11},"exposure":{"exposureLevel":"goodExposure","value":0.64},"noise":{"noiseLevel":"low","value":0.0},"makeup":{"eyeMakeup":false,"lipMakeup":false},"accessories":[],"occlusion":{"foreheadOccluded":false,"eyeOccluded":false,"mouthOccluded":false},"hair":{"bald":0.85,"invisible":false,"hairColor":[]}}}]