[{"faceId":"49ee7266-affb-4a13-99d2-a33cd6addb91","faceRectangle":{"top":40,"left":29,"width":70,"height":70},"faceAttributes":{"smile":0.973,"headPose":{"pitch":-9.7,"roll":1.7,"yaw":-4.6},"gender":"female","age":20.0,"facialHair":{"moustache":0.0,"beard":0.0,"sideburns":0.0},"glasses":"NoGlasses","emotion":{"anger":0.0,"contempt":0.0,"disgust":0.0,"fear":0.0,"happiness":0.973,"neutral":0.027,"sadness":0.0,"surprise":0.0},"blur":{"blurLevel":"high","value":0.82},"exposure":{"exposureLevel":"goodExposure","value":0.47},"noise":{"noiseLevel":"low","value":0.0},"makeup":{"eyeMakeup":true,"lipMakeup":false},"accessories":[],"occlusion":{"foreheadOccluded":false,"eyeOccluded":false,"mouthOccluded":false},"hair":{"bald":0.05,"invisible":false,"hairColor":[{"color":"black","confidence":0.99},{"color":"brown","confidence":0.91},{"color":"gray","confidence":0.33},{"color":"other","confidence":0.33},{"color":"blond","confidence":0.05},{"color":"red","confidence":0.04}]}}}]