[{"faceId":"65188bd3-947a-4828-8eac-71df4fd0b92c","faceRectangle":{"top":38,"left":24,"width":77,"height":77},"faceAttributes":{"smile":0.999,"headPose":{"pitch":-0.5,"roll":0.8,"yaw":-20.6},"gender":"female","age":37.0,"facialHair":{"moustache":0.0,"beard":0.0,"sideburns":0.0},"glasses":"NoGlasses","emotion":{"anger":0.0,"contempt":0.0,"disgust":0.0,"fear":0.0,"happiness":0.999,"neutral":0.0,"sadness":0.0,"surprise":0.0},"blur":{"blurLevel":"low","value":0.0},"exposure":{"exposureLevel":"goodExposure","value":0.48},"noise":{"noiseLevel":"low","value":0.06},"makeup":{"eyeMakeup":true,"lipMakeup":true},"accessories":[{"type":"headwear","confidence":1.0}],"occlusion":{"foreheadOccluded":true,"eyeOccluded":false,"mouthOccluded":false},"hair":{"bald":0.0,"invisible":true,"hairColor":[]}}}]