[{"faceId":"bb4cb3d8-f2c4-4a49-ab85-940a9a0e7b7c","faceRectangle":{"top":40,"left":28,"width":69,"height":69},"faceAttributes":{"smile":0.001,"headPose":{"pitch":-1.9,"roll":1.1,"yaw":-20.3},"gender":"female","age":2.0,"facialHair":{"moustache":0.0,"beard":0.0,"sideburns":0.0},"glasses":"NoGlasses","emotion":{"anger":0.013,"contempt":0.003,"disgust":0.001,"fear":0.011,"happiness":0.001,"neutral":0.876,"sadness":0.02,"surprise":0.075},"blur":{"blurLevel":"medium","value":0.61},"exposure":{"exposureLevel":"goodExposure","value":0.63},"noise":{"noiseLevel":"low","value":0.0},"makeup":{"eyeMakeup":true,"lipMakeup":false},"accessories":[],"occlusion":{"foreheadOccluded":false,"eyeOccluded":false,"mouthOccluded":false},"hair":{"bald":0.07,"invisible":false,"hairColor":[{"color":"blond","confidence":0.98},{"color":"brown","confidence":0.93},{"color":"red","confidence":0.79},{"color":"gray","confidence":0.18},{"color":"other","confidence":0.15},{"color":"black","confidence":0.01}]}}}]