[{"faceId":"42bf56ba-9c56-4bc1-b9f4-61d9a766e6a7","faceRectangle":{"top":40,"left":27,"width":73,"height":73},"faceAttributes":{"smile":0.004,"headPose":{"pitch":-13.9,"roll":1.2,"yaw":-7.7},"gender":"female","age":9.0,"facialHair":{"moustache":0.0,"beard":0.0,"sideburns":0.0},"glasses":"NoGlasses","emotion":{"anger":0.0,"contempt":0.0,"disgust":0.0,"fear":0.0,"happiness":0.004,"neutral":0.979,"sadness":0.017,"surprise":0.0},"blur":{"blurLevel":"low","value":0.12},"exposure":{"exposureLevel":"goodExposure","value":0.65},"noise":{"noiseLevel":"low","value":0.0},"makeup":{"eyeMakeup":false,"lipMakeup":false},"accessories":[{"type":"headwear","confidence":1.0}],"occlusion":{"foreheadOccluded":true,"eyeOccluded":false,"mouthOccluded":false},"hair":{"bald":0.0,"invisible":true,"hairColor":[]}}}]