[{"faceId":"2c7115dc-fc34-47a8-aec0-acdd244a8a34","faceRectangle":{"top":40,"left":24,"width":74,"height":74},"faceAttributes":{"smile":0.804,"headPose":{"pitch":-0.5,"roll":0.2,"yaw":-36.9},"gender":"female","age":23.0,"facialHair":{"moustache":0.0,"beard":0.0,"sideburns":0.0},"glasses":"NoGlasses","emotion":{"anger":0.0,"contempt":0.005,"disgust":0.002,"fear":0.0,"happiness":0.804,"neutral":0.119,"sadness":0.068,"surprise":0.001},"blur":{"blurLevel":"low","value":0.0},"exposure":{"exposureLevel":"goodExposure","value":0.68},"noise":{"noiseLevel":"low","value":0.0},"makeup":{"eyeMakeup":true,"lipMakeup":true},"accessories":[],"occlusion":{"foreheadOccluded":false,"eyeOccluded":false,"mouthOccluded":false},"hair":{"bald":0.09,"invisible":false,"hairColor":[{"color":"black","confidence":0.97},{"color":"brown","confidence":0.96},{"color":"other","confidence":0.26},{"color":"gray","confidence":0.21},{"color":"red","confidence":0.13},{"color":"blond","confidence":0.1}]}}}]