[{"faceId":"c1372426-ae03-474b-b4ec-37ee81548f71","faceRectangle":{"top":40,"left":27,"width":72,"height":72},"faceAttributes":{"smile":1.0,"headPose":{"pitch":-10.6,"roll":0.3,"yaw":-20.3},"gender":"male","age":37.0,"facialHair":{"moustache":0.4,"beard":0.4,"sideburns":0.1},"glasses":"NoGlasses","emotion":{"anger":0.0,"contempt":0.0,"disgust":0.0,"fear":0.0,"happiness":1.0,"neutral":0.0,"sadness":0.0,"surprise":0.0},"blur":{"blurLevel":"medium","value":0.3},"exposure":{"exposureLevel":"goodExposure","value":0.7},"noise":{"noiseLevel":"low","value":0.21},"makeup":{"eyeMakeup":false,"lipMakeup":false},"accessories":[],"occlusion":{"foreheadOccluded":false,"eyeOccluded":false,"mouthOccluded":false},"hair":{"bald":0.09,"invisible":false,"hairColor":[{"color":"black","confidence":1.0},{"color":"gray","confidence":0.81},{"color":"brown","confidence":0.66},{"color":"other","confidence":0.52},{"color":"blond","confidence":0.01},{"color":"red","confidence":0.01}]}}}]