[{"faceId":"a1271195-ea85-4bb1-89d5-e42680dbc0d9","faceRectangle":{"top":42,"left":27,"width":71,"height":71},"faceAttributes":{"smile":0.0,"headPose":{"pitch":-6.3,"roll":-0.1,"yaw":11.9},"gender":"male","age":56.0,"facialHair":{"moustache":0.6,"beard":0.6,"sideburns":0.6},"glasses":"NoGlasses","emotion":{"anger":0.0,"contempt":0.0,"disgust":0.0,"fear":0.0,"happiness":0.0,"neutral":0.919,"sadness":0.001,"surprise":0.081},"blur":{"blurLevel":"low","value":0.0},"exposure":{"exposureLevel":"goodExposure","value":0.56},"noise":{"noiseLevel":"low","value":0.0},"makeup":{"eyeMakeup":false,"lipMakeup":false},"accessories":[],"occlusion":{"foreheadOccluded":false,"eyeOccluded":false,"mouthOccluded":false},"hair":{"bald":0.33,"invisible":false,"hairColor":[{"color":"gray","confidence":1.0},{"color":"blond","confidence":0.81},{"color":"black","confidence":0.69},{"color":"other","confidence":0.39},{"color":"brown","confidence":0.14},{"color":"red","confidence":0.01}]}}}]