[{"faceId":"6f07bc08-071c-4eb6-bedc-fc433b2faeb0","faceRectangle":{"top":42,"left":33,"width":61,"height":61},"faceAttributes":{"smile":0.999,"headPose":{"pitch":10.8,"roll":-1.1,"yaw":-5.9},"gender":"male","age":0.0,"facialHair":{"moustache":0.0,"beard":0.0,"sideburns":0.0},"glasses":"NoGlasses","emotion":{"anger":0.0,"contempt":0.0,"disgust":0.0,"fear":0.0,"happiness":0.999,"neutral":0.001,"sadness":0.0,"surprise":0.0},"blur":{"blurLevel":"medium","value":0.4},"exposure":{"exposureLevel":"goodExposure","value":0.7},"noise":{"noiseLevel":"low","value":0.09},"makeup":{"eyeMakeup":false,"lipMakeup":false},"accessories":[],"occlusion":{"foreheadOccluded":false,"eyeOccluded":false,"mouthOccluded":false},"hair":{"bald":0.1,"invisible":false,"hairColor":[{"color":"blond","confidence":0.98},{"color":"brown","confidence":0.54},{"color":"red","confidence":0.36},{"color":"other","confidence":0.35},{"color":"gray","confidence":0.33},{"color":"black","confidence":0.12}]}}}]