[{"faceId":"11e4ad37-c725-4f43-a0f7-1f7a95a3a86f","faceRectangle":{"top":40,"left":30,"width":69,"height":69},"faceAttributes":{"smile":0.999,"headPose":{"pitch":-5.8,"roll":1.6,"yaw":15.3},"gender":"female","age":28.0,"facialHair":{"moustache":0.0,"beard":0.0,"sideburns":0.0},"glasses":"NoGlasses","emotion":{"anger":0.0,"contempt":0.0,"disgust":0.0,"fear":0.0,"happiness":0.999,"neutral":0.001,"sadness":0.0,"surprise":0.0},"blur":{"blurLevel":"low","value":0.17},"exposure":{"exposureLevel":"goodExposure","value":0.69},"noise":{"noiseLevel":"low","value":0.3},"makeup":{"eyeMakeup":true,"lipMakeup":true},"accessories":[],"occlusion":{"foreheadOccluded":false,"eyeOccluded":true,"mouthOccluded":false},"hair":{"bald":0.16,"invisible":false,"hairColor":[{"color":"blond","confidence":1.0},{"color":"gray","confidence":0.97},{"color":"other","confidence":0.31},{"color":"brown","confidence":0.05},{"color":"red","confidence":0.03},{"color":"black","confidence":0.02}]}}}]