[{"faceId":"f61e3bc6-5a8c-4342-92c8-4b62c661f259","faceRectangle":{"top":40,"left":28,"width":72,"height":72},"faceAttributes":{"smile":1.0,"headPose":{"pitch":-3.5,"roll":-0.6,"yaw":-1.1},"gender":"female","age":19.0,"facialHair":{"moustache":0.0,"beard":0.0,"sideburns":0.0},"glasses":"NoGlasses","emotion":{"anger":0.0,"contempt":0.0,"disgust":0.0,"fear":0.0,"happiness":1.0,"neutral":0.0,"sadness":0.0,"surprise":0.0},"blur":{"blurLevel":"medium","value":0.42},"exposure":{"exposureLevel":"goodExposure","value":0.64},"noise":{"noiseLevel":"low","value":0.0},"makeup":{"eyeMakeup":true,"lipMakeup":true},"accessories":[],"occlusion":{"foreheadOccluded":false,"eyeOccluded":false,"mouthOccluded":false},"hair":{"bald":0.15,"invisible":false,"hairColor":[{"color":"black","confidence":0.97},{"color":"brown","confidence":0.94},{"color":"gray","confidence":0.4},{"color":"other","confidence":0.21},{"color":"blond","confidence":0.13},{"color":"red","confidence":0.06}]}}}]