[{"faceId":"ef2b1125-eab8-49d6-877c-aa650f61eed7","faceRectangle":{"top":41,"left":26,"width":73,"height":73},"faceAttributes":{"smile":0.189,"headPose":{"pitch":-1.4,"roll":0.1,"yaw":-28.7},"gender":"female","age":22.0,"facialHair":{"moustache":0.0,"beard":0.0,"sideburns":0.0},"glasses":"NoGlasses","emotion":{"anger":0.0,"contempt":0.0,"disgust":0.0,"fear":0.0,"happiness":0.189,"neutral":0.804,"sadness":0.001,"surprise":0.006},"blur":{"blurLevel":"medium","value":0.3},"exposure":{"exposureLevel":"overExposure","value":0.92},"noise":{"noiseLevel":"medium","value":0.36},"makeup":{"eyeMakeup":true,"lipMakeup":true},"accessories":[],"occlusion":{"foreheadOccluded":false,"eyeOccluded":false,"mouthOccluded":false},"hair":{"bald":0.11,"invisible":false,"hairColor":[{"color":"brown","confidence":0.96},{"color":"red","confidence":0.82},{"color":"black","confidence":0.53},{"color":"other","confidence":0.4},{"color":"blond","confidence":0.18},{"color":"gray","confidence":0.05}]}}}]