[{"faceId":"735d919f-a1b8-4faa-bd99-928aaf719c89","faceRectangle":{"top":40,"left":28,"width":72,"height":72},"faceAttributes":{"smile":0.082,"headPose":{"pitch":6.5,"roll":1.4,"yaw":5.3},"gender":"female","age":16.0,"facialHair":{"moustache":0.0,"beard":0.0,"sideburns":0.0},"glasses":"ReadingGlasses","emotion":{"anger":0.0,"contempt":0.001,"disgust":0.0,"fear":0.0,"happiness":0.082,"neutral":0.916,"sadness":0.001,"surprise":0.0},"blur":{"blurLevel":"low","value":0.02},"exposure":{"exposureLevel":"goodExposure","value":0.74},"noise":{"noiseLevel":"low","value":0.0},"makeup":{"eyeMakeup":false,"lipMakeup":false},"accessories":[{"type":"glasses","confidence":0.95}],"occlusion":{"foreheadOccluded":false,"eyeOccluded":false,"mouthOccluded":false},"hair":{"bald":0.08,"invisible":false,"hairColor":[{"color":"black","confidence":0.98},{"color":"brown","confidence":0.88},{"color":"blond","confidence":0.27},{"color":"other","confidence":0.27},{"color":"gray","confidence":0.25},{"color":"red","confidence":0.06}]}}}]