[{"faceId":"7e85627c-b047-4ac7-a96b-80ef2f9e0477","faceRectangle":{"top":39,"left":26,"width":73,"height":73},"faceAttributes":{"smile":0.021,"headPose":{"pitch":-5.8,"roll":-1.6,"yaw":-25.6},"gender":"female","age":23.0,"facialHair":{"moustache":0.0,"beard":0.0,"sideburns":0.0},"glasses":"NoGlasses","emotion":{"anger":0.0,"contempt":0.0,"disgust":0.0,"fear":0.0,"happiness":0.021,"neutral":0.975,"sadness":0.004,"surprise":0.0},"blur":{"blurLevel":"low","value":0.04},"exposure":{"exposureLevel":"goodExposure","value":0.66},"noise":{"noiseLevel":"low","value":0.0},"makeup":{"eyeMakeup":true,"lipMakeup":true},"accessories":[],"occlusion":{"foreheadOccluded":false,"eyeOccluded":false,"mouthOccluded":false},"hair":{"bald":0.04,"invisible":false,"hairColor":[{"color":"red","confidence":1.0},{"color":"other","confidence":0.83},{"color":"brown","confidence":0.81},{"color":"blond","confidence":0.44},{"color":"gray","confidence":0.01},{"color":"black","confidence":0.01}]}}}]