[{"faceId":"6e9e17ec-60a5-41ac-a2a3-db0b09ea45b7","faceRectangle":{"top":49,"left":29,"width":63,"height":63},"faceAttributes":{"smile":0.977,"headPose":{"pitch":-16.6,"roll":-6.3,"yaw":-16.2},"gender":"female","age":51.0,"facialHair":{"moustache":0.0,"beard":0.0,"sideburns":0.0},"glasses":"NoGlasses","emotion":{"anger":0.0,"contempt":0.013,"disgust":0.0,"fear":0.0,"happiness":0.977,"neutral":0.009,"sadness":0.0,"surprise":0.0},"blur":{"blurLevel":"low","value":0.0},"exposure":{"exposureLevel":"goodExposure","value":0.54},"noise":{"noiseLevel":"low","value":0.0},"makeup":{"eyeMakeup":false,"lipMakeup":true},"accessories":[{"type":"glasses","confidence":0.83},{"type":"headwear","confidence":1.0}],"occlusion":{"foreheadOccluded":true,"eyeOccluded":false,"mouthOccluded":false},"hair":{"bald":0.0,"invisible":true,"hairColor":[]}}}]