[{"faceId":"7d8d6602-7225-4d38-aa01-de546a33922c","faceRectangle":{"top":41,"left":29,"width":72,"height":72},"faceAttributes":{"smile":0.0,"headPose":{"pitch":-5.2,"roll":0.5,"yaw":-11.3},"gender":"male","age":44.0,"facialHair":{"moustache":0.6,"beard":0.6,"sideburns":0.6},"glasses":"NoGlasses","emotion":{"anger":0.001,"contempt":0.001,"disgust":0.0,"fear":0.0,"happiness":0.0,"neutral":0.983,"sadness":0.015,"surprise":0.0},"blur":{"blurLevel":"low","value":0.0},"exposure":{"exposureLevel":"goodExposure","value":0.62},"noise":{"noiseLevel":"low","value":0.0},"makeup":{"eyeMakeup":false,"lipMakeup":false},"accessories":[],"occlusion":{"foreheadOccluded":false,"eyeOccluded":true,"mouthOccluded":true},"hair":{"bald":0.05,"invisible":false,"hairColor":[{"color":"black","confidence":0.98},{"color":"brown","confidence":0.76},{"color":"gray","confidence":0.65},{"color":"other","confidence":0.45},{"color":"red","confidence":0.06},{"color":"blond","confidence":0.05}]}}}]