[{"faceId":"dbac16c9-1b2d-4bc3-a96b-d303fc20e6f8","faceRectangle":{"top":40,"left":26,"width":73,"height":73},"faceAttributes":{"smile":0.764,"headPose":{"pitch":0.6,"roll":0.4,"yaw":-19.2},"gender":"male","age":13.0,"facialHair":{"moustache":0.0,"beard":0.0,"sideburns":0.0},"glasses":"NoGlasses","emotion":{"anger":0.012,"contempt":0.003,"disgust":0.029,"fear":0.0,"happiness":0.764,"neutral":0.184,"sadness":0.006,"surprise":0.002},"blur":{"blurLevel":"low","value":0.0},"exposure":{"exposureLevel":"overExposure","value":0.75},"noise":{"noiseLevel":"low","value":0.16},"makeup":{"eyeMakeup":true,"lipMakeup":false},"accessories":[],"occlusion":{"foreheadOccluded":false,"eyeOccluded":false,"mouthOccluded":false},"hair":{"bald":0.02,"invisible":false,"hairColor":[{"color":"brown","confidence":0.98},{"color":"black","confidence":0.98},{"color":"red","confidence":0.22},{"color":"other","confidence":0.18},{"color":"blond","confidence":0.11},{"color":"gray","confidence":0.05}]}}}]