[{"faceId":"62a59dda-af90-40b9-8c84-62883b2ffb7a","faceRectangle":{"top":40,"left":26,"width":75,"height":75},"faceAttributes":{"smile":0.001,"headPose":{"pitch":-20.9,"roll":-2.0,"yaw":-20.0},"gender":"female","age":24.0,"facialHair":{"moustache":0.0,"beard":0.0,"sideburns":0.0},"glasses":"NoGlasses","emotion":{"anger":0.0,"contempt":0.0,"disgust":0.0,"fear":0.0,"happiness":0.001,"neutral":0.907,"sadness":0.092,"surprise":0.0},"blur":{"blurLevel":"medium","value":0.32},"exposure":{"exposureLevel":"goodExposure","value":0.61},"noise":{"noiseLevel":"low","value":0.02},"makeup":{"eyeMakeup":true,"lipMakeup":false},"accessories":[],"occlusion":{"foreheadOccluded":false,"eyeOccluded":false,"mouthOccluded":false},"hair":{"bald":0.03,"invisible":false,"hairColor":[{"color":"brown","confidence":0.97},{"color":"blond","confidence":0.89},{"color":"gray","confidence":0.77},{"color":"black","confidence":0.11},{"color":"red","confidence":0.11},{"color":"other","confidence":0.07}]}}}]