[{"faceId":"96294626-eb08-495e-bac8-e9a7e1d97cef","faceRectangle":{"top":38,"left":28,"width":74,"height":74},"faceAttributes":{"smile":0.092,"headPose":{"pitch":20.6,"roll":1.9,"yaw":13.7},"gender":"male","age":40.0,"facialHair":{"moustache":0.1,"beard":0.1,"sideburns":0.1},"glasses":"NoGlasses","emotion":{"anger":0.0,"contempt":0.0,"disgust":0.0,"fear":0.0,"happiness":0.092,"neutral":0.732,"sadness":0.0,"surprise":0.175},"blur":{"blurLevel":"medium","value":0.64},"exposure":{"exposureLevel":"goodExposure","value":0.6},"noise":{"noiseLevel":"low","value":0.0},"makeup":{"eyeMakeup":false,"lipMakeup":false},"accessories":[],"occlusion":{"foreheadOccluded":false,"eyeOccluded":false,"mouthOccluded":false},"hair":{"bald":0.04,"invisible":false,"hairColor":[{"color":"brown","confidence":0.99},{"color":"black","confidence":0.97},{"color":"gray","confidence":0.27},{"color":"other","confidence":0.2},{"color":"red","confidence":0.15},{"color":"blond","confidence":0.03}]}}}]