[{"faceId":"549e80f3-b289-45ad-b442-b743430a4f71","faceRectangle":{"top":40,"left":26,"width":74,"height":74},"faceAttributes":{"smile":0.064,"headPose":{"pitch":3.2,"roll":-0.3,"yaw":-18.9},"gender":"female","age":45.0,"facialHair":{"moustache":0.0,"beard":0.0,"sideburns":0.0},"glasses":"NoGlasses","emotion":{"anger":0.012,"contempt":0.0,"disgust":0.002,"fear":0.013,"happiness":0.064,"neutral":0.608,"sadness":0.117,"surprise":0.183},"blur":{"blurLevel":"medium","value":0.37},"exposure":{"exposureLevel":"goodExposure","value":0.59},"noise":{"noiseLevel":"low","value":0.18},"makeup":{"eyeMakeup":true,"lipMakeup":true},"accessories":[],"occlusion":{"foreheadOccluded":false,"eyeOccluded":false,"mouthOccluded":false},"hair":{"bald":0.02,"invisible":false,"hairColor":[{"color":"black","confidence":1.0},{"color":"brown","confidence":0.76},{"color":"gray","confidence":0.57},{"color":"other","confidence":0.41},{"color":"blond","confidence":0.03},{"color":"red","confidence":0.01}]}}}]