[{"faceId":"7040daae-7855-437a-b7d8-ef76d1025165","faceRectangle":{"top":41,"left":29,"width":70,"height":70},"faceAttributes":{"smile":0.342,"headPose":{"pitch":-6.1,"roll":-0.2,"yaw":-10.5},"gender":"female","age":22.0,"facialHair":{"moustache":0.0,"beard":0.0,"sideburns":0.0},"glasses":"NoGlasses","emotion":{"anger":0.0,"contempt":0.001,"disgust":0.0,"fear":0.0,"happiness":0.342,"neutral":0.657,"sadness":0.0,"surprise":0.0},"blur":{"blurLevel":"low","value":0.09},"exposure":{"exposureLevel":"overExposure","value":0.76},"noise":{"noiseLevel":"low","value":0.22},"makeup":{"eyeMakeup":true,"lipMakeup":true},"accessories":[],"occlusion":{"foreheadOccluded":false,"eyeOccluded":false,"mouthOccluded":false},"hair":{"bald":0.19,"invisible":false,"hairColor":[{"color":"black","confidence":0.91},{"color":"brown","confidence":0.61},{"color":"other","confidence":0.54},{"color":"gray","confidence":0.45},{"color":"blond","confidence":0.3},{"color":"red","confidence":0.14}]}}}]