[{"faceId":"1a3d2643-49b5-450c-96b0-4091e5865854","faceRectangle":{"top":39,"left":25,"width":74,"height":74},"faceAttributes":{"smile":0.0,"headPose":{"pitch":22.8,"roll":2.9,"yaw":-13.3},"gender":"male","age":55.0,"facialHair":{"moustache":0.6,"beard":0.6,"sideburns":0.1},"glasses":"Sunglasses","emotion":{"anger":0.004,"contempt":0.0,"disgust":0.0,"fear":0.001,"happiness":0.0,"neutral":0.949,"sadness":0.001,"surprise":0.046},"blur":{"blurLevel":"medium","value":0.69},"exposure":{"exposureLevel":"goodExposure","value":0.67},"noise":{"noiseLevel":"medium","value":0.39},"makeup":{"eyeMakeup":false,"lipMakeup":false},"accessories":[{"type":"glasses","confidence":1.0}],"occlusion":{"foreheadOccluded":false,"eyeOccluded":false,"mouthOccluded":false},"hair":{"bald":0.01,"invisible":false,"hairColor":[{"color":"blond","confidence":0.99},{"color":"gray","confidence":0.92},{"color":"brown","confidence":0.34},{"color":"red","confidence":0.29},{"color":"other","confidence":0.28},{"color":"black","confidence":0.01}]}}}]