[{"faceId":"622e6377-16d6-4efd-90b0-d3bbd5ddf94b","faceRectangle":{"top":42,"left":28,"width":72,"height":72},"faceAttributes":{"smile":0.0,"headPose":{"pitch":-15.4,"roll":3.1,"yaw":18.3},"gender":"male","age":39.0,"facialHair":{"moustache":0.4,"beard":0.4,"sideburns":0.1},"glasses":"NoGlasses","emotion":{"anger":0.011,"contempt":0.005,"disgust":0.006,"fear":0.0,"happiness":0.0,"neutral":0.843,"sadness":0.136,"surprise":0.0},"blur":{"blurLevel":"medium","value":0.69},"exposure":{"exposureLevel":"goodExposure","value":0.69},"noise":{"noiseLevel":"medium","value":0.37},"makeup":{"eyeMakeup":false,"lipMakeup":false},"accessories":[],"occlusion":{"foreheadOccluded":false,"eyeOccluded":false,"mouthOccluded":false},"hair":{"bald":0.17,"invisible":false,"hairColor":[{"color":"black","confidence":0.98},{"color":"gray","confidence":0.91},{"color":"brown","confidence":0.74},{"color":"blond","confidence":0.33},{"color":"other","confidence":0.22},{"color":"red","confidence":0.01}]}}}]