[{"faceId":"363ecc3e-d269-4bdc-8553-fd06183d7997","faceRectangle":{"top":41,"left":28,"width":72,"height":72},"faceAttributes":{"smile":0.0,"headPose":{"pitch":-9.2,"roll":2.7,"yaw":18.4},"gender":"male","age":24.0,"facialHair":{"moustache":0.1,"beard":0.1,"sideburns":0.1},"glasses":"NoGlasses","emotion":{"anger":0.0,"contempt":0.0,"disgust":0.0,"fear":0.0,"happiness":0.0,"neutral":0.908,"sadness":0.092,"surprise":0.0},"blur":{"blurLevel":"medium","value":0.49},"exposure":{"exposureLevel":"goodExposure","value":0.66},"noise":{"noiseLevel":"low","value":0.01},"makeup":{"eyeMakeup":false,"lipMakeup":false},"accessories":[],"occlusion":{"foreheadOccluded":false,"eyeOccluded":false,"mouthOccluded":false},"hair":{"bald":0.28,"invisible":false,"hairColor":[{"color":"black","confidence":0.95},{"color":"brown","confidence":0.88},{"color":"gray","confidence":0.44},{"color":"other","confidence":0.27},{"color":"blond","confidence":0.22},{"color":"red","confidence":0.08}]}}}]