[{"faceId":"fe236823-19f2-49c0-8e1a-299b0981800f","faceRectangle":{"top":38,"left":26,"width":75,"height":75},"faceAttributes":{"smile":0.106,"headPose":{"pitch":6.3,"roll":2.5,"yaw":8.0},"gender":"female","age":57.0,"facialHair":{"moustache":0.0,"beard":0.0,"sideburns":0.0},"glasses":"NoGlasses","emotion":{"anger":0.0,"contempt":0.0,"disgust":0.0,"fear":0.0,"happiness":0.106,"neutral":0.892,"sadness":0.0,"surprise":0.001},"blur":{"blurLevel":"medium","value":0.41},"exposure":{"exposureLevel":"goodExposure","value":0.66},"noise":{"noiseLevel":"medium","value":0.58},"makeup":{"eyeMakeup":true,"lipMakeup":true},"accessories":[],"occlusion":{"foreheadOccluded":false,"eyeOccluded":false,"mouthOccluded":false},"hair":{"bald":0.02,"invisible":false,"hairColor":[{"color":"blond","confidence":1.0},{"color":"brown","confidence":0.76},{"color":"red","confidence":0.52},{"color":"gray","confidence":0.47},{"color":"other","confidence":0.17},{"color":"black","confidence":0.01}]}}}]