[{"faceId":"0d6e3b48-7613-421d-9da6-a5fb87e76efc","faceRectangle":{"top":40,"left":28,"width":73,"height":73},"faceAttributes":{"smile":0.0,"headPose":{"pitch":-20.3,"roll":2.9,"yaw":12.5},"gender":"male","age":3.0,"facialHair":{"moustache":0.0,"beard":0.0,"sideburns":0.0},"glasses":"NoGlasses","emotion":{"anger":0.0,"contempt":0.0,"disgust":0.0,"fear":0.0,"happiness":0.0,"neutral":0.782,"sadness":0.218,"surprise":0.0},"blur":{"blurLevel":"medium","value":0.49},"exposure":{"exposureLevel":"goodExposure","value":0.49},"noise":{"noiseLevel":"low","value":0.15},"makeup":{"eyeMakeup":false,"lipMakeup":false},"accessories":[],"occlusion":{"foreheadOccluded":false,"eyeOccluded":false,"mouthOccluded":false},"hair":{"bald":0.06,"invisible":false,"hairColor":[{"color":"blond","confidence":1.0},{"color":"brown","confidence":0.45},{"color":"gray","confidence":0.45},{"color":"red","confidence":0.41},{"color":"other","confidence":0.25},{"color":"black","confidence":0.01}]}}}]