[{"faceId":"f3adc7dd-9c0f-48da-91a2-8cb896730e42","faceRectangle":{"top":40,"left":21,"width":76,"height":76},"faceAttributes":{"smile":0.011,"headPose":{"pitch":11.4,"roll":0.5,"yaw":-27.6},"gender":"female","age":40.0,"facialHair":{"moustache":0.0,"beard":0.0,"sideburns":0.0},"glasses":"NoGlasses","emotion":{"anger":0.005,"contempt":0.0,"disgust":0.0,"fear":0.001,"happiness":0.011,"neutral":0.315,"sadness":0.0,"surprise":0.667},"blur":{"blurLevel":"low","value":0.0},"exposure":{"exposureLevel":"overExposure","value":0.82},"noise":{"noiseLevel":"low","value":0.0},"makeup":{"eyeMakeup":true,"lipMakeup":true},"accessories":[],"occlusion":{"foreheadOccluded":false,"eyeOccluded":false,"mouthOccluded":false},"hair":{"bald":0.1,"invisible":false,"hairColor":[{"color":"blond","confidence":1.0},{"color":"gray","confidence":0.74},{"color":"other","confidence":0.68},{"color":"red","confidence":0.23},{"color":"black","confidence":0.04},{"color":"brown","confidence":0.03}]}}}]