[{"faceId":"88faac19-9bc2-4d87-891a-944eef451b6f","faceRectangle":{"top":39,"left":26,"width":75,"height":75},"faceAttributes":{"smile":0.998,"headPose":{"pitch":0.4,"roll":1.5,"yaw":-14.1},"gender":"male","age":49.0,"facialHair":{"moustache":0.4,"beard":0.4,"sideburns":0.4},"glasses":"NoGlasses","emotion":{"anger":0.0,"contempt":0.0,"disgust":0.0,"fear":0.0,"happiness":0.998,"neutral":0.002,"sadness":0.0,"surprise":0.0},"blur":{"blurLevel":"low","value":0.0},"exposure":{"exposureLevel":"goodExposure","value":0.74},"noise":{"noiseLevel":"medium","value":0.6},"makeup":{"eyeMakeup":false,"lipMakeup":false},"accessories":[{"type":"headwear","confidence":0.99}],"occlusion":{"foreheadOccluded":true,"eyeOccluded":false,"mouthOccluded":false},"hair":{"bald":0.0,"invisible":true,"hairColor":[]}}}]