[{"faceId":"d16d0e4e-3345-4eac-9ea2-fb5da758107c","faceRectangle":{"top":40,"left":29,"width":70,"height":70},"faceAttributes":{"smile":1.0,"headPose":{"pitch":-1.3,"roll":-0.7,"yaw":2.5},"gender":"female","age":13.0,"facialHair":{"moustache":0.0,"beard":0.0,"sideburns":0.0},"glasses":"NoGlasses","emotion":{"anger":0.0,"contempt":0.0,"disgust":0.0,"fear":0.0,"happiness":1.0,"neutral":0.0,"sadness":0.0,"surprise":0.0},"blur":{"blurLevel":"medium","value":0.25},"exposure":{"exposureLevel":"goodExposure","value":0.71},"noise":{"noiseLevel":"medium","value":0.4},"makeup":{"eyeMakeup":true,"lipMakeup":false},"accessories":[],"occlusion":{"foreheadOccluded":false,"eyeOccluded":false,"mouthOccluded":false},"hair":{"bald":0.01,"invisible":false,"hairColor":[{"color":"brown","confidence":0.99},{"color":"black","confidence":0.61},{"color":"blond","confidence":0.39},{"color":"gray","confidence":0.25},{"color":"red","confidence":0.22},{"color":"other","confidence":0.08}]}}}]