[{"faceId":"cdbd4090-a6ab-4206-8cad-3ae46582b66a","faceRectangle":{"top":41,"left":28,"width":71,"height":71},"faceAttributes":{"smile":0.454,"headPose":{"pitch":-2.5,"roll":1.3,"yaw":-1.8},"gender":"female","age":10.0,"facialHair":{"moustache":0.0,"beard":0.0,"sideburns":0.0},"glasses":"NoGlasses","emotion":{"anger":0.0,"contempt":0.0,"disgust":0.0,"fear":0.0,"happiness":0.454,"neutral":0.546,"sadness":0.0,"surprise":0.0},"blur":{"blurLevel":"medium","value":0.37},"exposure":{"exposureLevel":"goodExposure","value":0.57},"noise":{"noiseLevel":"medium","value":0.31},"makeup":{"eyeMakeup":false,"lipMakeup":true},"accessories":[],"occlusion":{"foreheadOccluded":false,"eyeOccluded":false,"mouthOccluded":false},"hair":{"bald":0.04,"invisible":false,"hairColor":[{"color":"black","confidence":1.0},{"color":"brown","confidence":0.88},{"color":"other","confidence":0.39},{"color":"gray","confidence":0.22},{"color":"red","confidence":0.04},{"color":"blond","confidence":0.02}]}}}]