[{"faceId":"6f348251-6e80-4669-b5db-5466f7ccf787","faceRectangle":{"top":39,"left":31,"width":66,"height":66},"faceAttributes":{"smile":1.0,"headPose":{"pitch":5.5,"roll":2.2,"yaw":-2.2},"gender":"female","age":23.0,"facialHair":{"moustache":0.0,"beard":0.0,"sideburns":0.0},"glasses":"Sunglasses","emotion":{"anger":0.0,"contempt":0.0,"disgust":0.0,"fear":0.0,"happiness":1.0,"neutral":0.0,"sadness":0.0,"surprise":0.0},"blur":{"blurLevel":"low","value":0.02},"exposure":{"exposureLevel":"goodExposure","value":0.42},"noise":{"noiseLevel":"low","value":0.0},"makeup":{"eyeMakeup":true,"lipMakeup":false},"accessories":[{"type":"glasses","confidence":1.0},{"type":"headwear","confidence":1.0}],"occlusion":{"foreheadOccluded":true,"eyeOccluded":false,"mouthOccluded":false},"hair":{"bald":0.0,"invisible":true,"hairColor":[]}}}]