[{"faceId":"ddb6d66b-e103-4680-9141-de38aabc88c2","faceRectangle":{"top":41,"left":29,"width":68,"height":68},"faceAttributes":{"smile":0.602,"headPose":{"pitch":-5.1,"roll":3.4,"yaw":0.5},"gender":"female","age":18.0,"facialHair":{"moustache":0.0,"beard":0.0,"sideburns":0.0},"glasses":"NoGlasses","emotion":{"anger":0.0,"contempt":0.001,"disgust":0.0,"fear":0.0,"happiness":0.602,"neutral":0.397,"sadness":0.0,"surprise":0.0},"blur":{"blurLevel":"low","value":0.22},"exposure":{"exposureLevel":"goodExposure","value":0.66},"noise":{"noiseLevel":"low","value":0.0},"makeup":{"eyeMakeup":true,"lipMakeup":false},"accessories":[],"occlusion":{"foreheadOccluded":false,"eyeOccluded":false,"mouthOccluded":false},"hair":{"bald":0.16,"invisible":false,"hairColor":[{"color":"brown","confidence":0.98},{"color":"black","confidence":0.93},{"color":"gray","confidence":0.21},{"color":"blond","confidence":0.16},{"color":"other","confidence":0.16},{"color":"red","confidence":0.13}]}}}]