[{"faceId":"90cd673c-da1c-4c7c-9ae8-4d4393ace35f","faceRectangle":{"top":41,"left":26,"width":71,"height":71},"faceAttributes":{"smile":0.217,"headPose":{"pitch":-5.7,"roll":1.5,"yaw":-31.6},"gender":"female","age":63.0,"facialHair":{"moustache":0.0,"beard":0.0,"sideburns":0.0},"glasses":"ReadingGlasses","emotion":{"anger":0.098,"contempt":0.001,"disgust":0.027,"fear":0.049,"happiness":0.217,"neutral":0.153,"sadness":0.404,"surprise":0.052},"blur":{"blurLevel":"medium","value":0.5},"exposure":{"exposureLevel":"goodExposure","value":0.64},"noise":{"noiseLevel":"low","value":0.0},"makeup":{"eyeMakeup":false,"lipMakeup":true},"accessories":[{"type":"glasses","confidence":0.97}],"occlusion":{"foreheadOccluded":false,"eyeOccluded":false,"mouthOccluded":false},"hair":{"bald":0.11,"invisible":false,"hairColor":[{"color":"brown","confidence":0.96},{"color":"gray","confidence":0.88},{"color":"black","confidence":0.85},{"color":"blond","confidence":0.15},{"color":"other","confidence":0.12},{"color":"red","confidence":0.03}]}}}]