[{"faceId":"08243ca8-fc76-46d6-8dbc-fc1bb391f832","faceRectangle":{"top":39,"left":28,"width":73,"height":73},"faceAttributes":{"smile":1.0,"headPose":{"pitch":1.2,"roll":1.4,"yaw":13.9},"gender":"female","age":44.0,"facialHair":{"moustache":0.0,"beard":0.0,"sideburns":0.0},"glasses":"ReadingGlasses","emotion":{"anger":0.0,"contempt":0.0,"disgust":0.0,"fear":0.0,"happiness":1.0,"neutral":0.0,"sadness":0.0,"surprise":0.0},"blur":{"blurLevel":"low","value":0.0},"exposure":{"exposureLevel":"goodExposure","value":0.64},"noise":{"noiseLevel":"low","value":0.03},"makeup":{"eyeMakeup":false,"lipMakeup":false},"accessories":[{"type":"glasses","confidence":0.85}],"occlusion":{"foreheadOccluded":false,"eyeOccluded":false,"mouthOccluded":false},"hair":{"bald":0.06,"invisible":false,"hairColor":[{"color":"brown","confidence":1.0},{"color":"black","confidence":0.58},{"color":"red","confidence":0.31},{"color":"blond","confidence":0.21},{"color":"gray","confidence":0.17},{"color":"other","confidence":0.04}]}}}]