[{"faceId":"3196e8c1-b03d-4ad6-ad4d-c32f1b50fe29","faceRectangle":{"top":40,"left":30,"width":69,"height":69},"faceAttributes":{"smile":0.001,"headPose":{"pitch":2.5,"roll":2.7,"yaw":9.3},"gender":"male","age":58.0,"facialHair":{"moustache":0.6,"beard":0.6,"sideburns":0.1},"glasses":"NoGlasses","emotion":{"anger":0.006,"contempt":0.001,"disgust":0.0,"fear":0.0,"happiness":0.001,"neutral":0.991,"sadness":0.0,"surprise":0.0},"blur":{"blurLevel":"medium","value":0.25},"exposure":{"exposureLevel":"goodExposure","value":0.63},"noise":{"noiseLevel":"low","value":0.0},"makeup":{"eyeMakeup":false,"lipMakeup":false},"accessories":[{"type":"headwear","confidence":0.99}],"occlusion":{"foreheadOccluded":true,"eyeOccluded":false,"mouthOccluded":false},"hair":{"bald":0.0,"invisible":true,"hairColor":[]}}}]